{
    "anonymous": 0,
    "areaDistrict": "芙蓉区",
    "atsDirectPost": false,
    "bossAvatar": "https://img.bosszhipin.com/boss/avatar/avatar_9.png",
    "bossCert": 3,
    "bossName": "黄女士",
    "bossOnline": false,
    "bossTitle": "HR",
    "brandIndustry": "音乐/视频/阅读",
    "brandLogo": "https://img.bosszhipin.com/beijin/upload/com/workfeel/20210519/e0a3abdd759ca2151420b834b9e75637cd0abc3f0a3ceeb37b0f0f506fd4a7b3.jpg",
    "brandName": "笔尚文化",
    "brandScaleName": "20-99人",
    "brandStageName": "不需要融资",
    "businessDistrict": "定王台",
    "city": 101250100,
    "cityName": "长沙",
    "contact": false,
    "daysPerWeekDesc": "",
    "encryptBossId": "678487ef40a3f6fc0nd529W9EFdR",
    "encryptBrandId": "79a023953635b1c71nZ-2d69Eg~~",
    "encryptJobId": "c5e6fae68982f79b1XR53Ni-FlpT",
    "expectId": 0,
    "goldHunter": 0,
    "gps": {
        "latitude": 28.193836,
        "longitude": 112.983359
    },
    "iconFlagList": [],
    "iconWord": "",
    "industry": 100011,
    "isShield": 0,
    "itemId": 273,
    "jobDegree": "大专",
    "jobExperience": "1年以内",
    "jobLabels": [
        "1年以内",
        "大专"
    ],
    "jobName": "小说广告文案专员【芙蓉广场】",
    "jobType": 0,
    "jobValidStatus": 1,
    "leastMonthDesc": "",
    "lid": "Nz3PU3ZYyG.search.273",
    "optimal": 0,
    "outland": 0,
    "proxyJob": 0,
    "proxyType": 0,
    "salaryDesc": "4-6K",
    "securityId": "uOP1P65a-Te2R-21QaCIUvb6-syIMSh0zPeilHevFBS5VYsLTteTrnS2P_GHDLSmJ8Z2uwKFaT2qCtOr7x7noSqsuKJd0rpYa6pqDJ8k3_qKSi2L7lE~",
    "showTopPosition": false,
    "skills": [
        "网络广告",
        "新媒体广告",
        "甲方经验",
        "全职"
    ],
    "welfareList": [
        "五险一金",
        "全勤奖",
        "零食下午茶",
        "员工旅游",
        "带薪年假",
        "节日福利"
    ]
}