{
    "anonymous": 0,
    "areaDistrict": "郫都区",
    "atsDirectPost": false,
    "bossAvatar": "https://img.bosszhipin.com/beijin/upload/avatar/20230302/607f1f3d68754fd0bf5fc8c097bcde08221a2db97c1397601ed727cb0f1582115d427053dfb734f1_s.png",
    "bossCert": 3,
    "bossName": "黄毅",
    "bossOnline": false,
    "bossTitle": "招聘者",
    "brandIndustry": "工程施工",
    "brandLogo": "https://img.bosszhipin.com/beijin/app/mobile/normal-0e3f1e4441a21d4874cece3a3d81f0fe.png",
    "brandName": "川谷消防",
    "brandScaleName": "20-99人",
    "brandStageName": "",
    "businessDistrict": "红光镇",
    "city": 101270100,
    "cityName": "成都",
    "contact": false,
    "daysPerWeekDesc": "",
    "encryptBossId": "024574eb54c1252c0nx-2tu8E1JX",
    "encryptBrandId": "43c819cd148461cf1nZ-29u-EVA~",
    "encryptJobId": "a4b6ea00a00682211HZ83NS9GVJW",
    "expectId": 975728182,
    "goldHunter": 0,
    "gps": null,
    "iconFlagList": [],
    "iconWord": "",
    "industry": 100702,
    "isShield": 0,
    "itemId": 295,
    "jobDegree": "本科",
    "jobExperience": "经验不限",
    "jobLabels": [
        "经验不限",
        "本科"
    ],
    "jobName": "储备工程师",
    "jobType": 0,
    "jobValidStatus": 1,
    "leastMonthDesc": "",
    "lid": "8klvc0zfTgT.search.295",
    "optimal": 0,
    "outland": 0,
    "proxyJob": 0,
    "proxyType": 0,
    "salaryDesc": "3-5K",
    "securityId": "5pKDZBQMqROi6-11oTwf0WbxvU-v9uCqLbp6MJXhrbVSkI3PPy87qpDnLZ96Hm2molQJtngobmTEXrcMyKnyOVq1kkRP1SDe6DPJ_VJfUUq_cFsfitq1ydxnU0TjO4JKZgs8t80NfcNk7Q~~",
    "showTopPosition": false,
    "skills": [
        "工程项目"
    ],
    "welfareList": []
}