{
    "afterNameIcons": [],
    "anonymous": 0,
    "areaDistrict": "雁塔区",
    "atsDirectPost": false,
    "beforeNameIcons": [],
    "bossAvatar": "https://img.bosszhipin.com/beijin/upload/avatar/20230407/607f1f3d68754fd09d95a258bed78ac38776a728473bf32a9f6f5f2c5339fa1e726748b2b71fbdc8_s.png",
    "bossCert": 3,
    "bossName": "于先生",
    "bossOnline": true,
    "bossTitle": "人事经理",
    "brandIndustry": "计算机服务",
    "brandLogo": "https://img.bosszhipin.com/beijin/mcs/chatphoto/20181020/175cda3d1e2e6ee15f82360a6a2c48bab108bfd88a38db8147fb0f41121e4e1b.jpg",
    "brandName": "鼎格工业软件",
    "brandScaleName": "20-99人",
    "brandStageName": "A轮",
    "businessDistrict": "高新路",
    "city": 101110100,
    "cityName": "西安",
    "contact": false,
    "daysPerWeekDesc": "",
    "encryptBossId": "d605af974a5a1e4a0nF53N-1F1tW",
    "encryptBrandId": "f4da1d157d220b101nB709u9FQ~~",
    "encryptJobId": "e01e7d2ccb367c8103Z92d2_EFNV",
    "expectId": 1014042683,
    "goldHunter": 0,
    "gps": {
        "latitude": 34.224927,
        "longitude": 108.906286
    },
    "iconFlagList": [],
    "iconWord": "",
    "industry": 100023,
    "isShield": 0,
    "itemId": 265,
    "jobDegree": "本科",
    "jobExperience": "1-3年",
    "jobLabels": [
        "1-3年",
        "本科"
    ],
    "jobName": "软件开发工程师（西安）",
    "jobType": 0,
    "jobValidStatus": 1,
    "leastMonthDesc": "",
    "lid": "9Z26EFSM2mB.search.265",
    "optimal": 0,
    "outland": 0,
    "proxyJob": 0,
    "proxyType": 0,
    "salaryDesc": "9-12K·14薪",
    "securityId": "oUDxKcjWHK3Ka-M1OcnxU1w7HRKvw9SImAClazZw81qAO4lt68Q8tVQ7z_Xdg29bI-4BcYxp9rYbO7m8jb6YDsaUlMJMzXUZDXPz3lMkm8KWkcXlpEzYexD_zpMp6HZtIs21wAEaOjF1D_vVJPujjXj5sXdGG2ydIUOnpRf2FxDEOxVMHw~~",
    "showTopPosition": false,
    "skills": [
        "JavaScript",
        "Vue",
        "Java",
        "C/C++",
        "Spring/Spring Boot",
        "MySQL/Redis/MongoDB",
        "计算机相关专业",
        "Linux",
        "QT"
    ],
    "welfareList": [
        "五险一金",
        "意外险",
        "交通补助",
        "通讯补贴",
        "节日福利",
        "餐补",
        "团建聚餐",
        "员工旅游",
        "定期体检",
        "年终奖",
        "带薪年假"
    ]
}