{
    "anonymous": 0,
    "areaDistrict": "历下区",
    "atsDirectPost": false,
    "bossAvatar": "https://img.bosszhipin.com/beijin/upload/tmp/20201117/fc163494734793969e8480b83d06e513cc4dd495f951d86abc07d11319f0ac36_s.jpg",
    "bossCert": 3,
    "bossName": "房女士",
    "bossOnline": false,
    "bossTitle": "工程中心部门经理",
    "brandIndustry": "计算机软件",
    "brandLogo": "https://img.bosszhipin.com/beijin/mcs/chatphoto/20200701/160a8fa3deadacd9dd3c1a40f022ceb27b0a82a1b9f4d45cef5568ce72979fd2_s.jpg",
    "brandName": "新思软件",
    "brandScaleName": "20-99人",
    "brandStageName": "未融资",
    "businessDistrict": "齐鲁软件园",
    "city": 101120100,
    "cityName": "济南",
    "contact": false,
    "daysPerWeekDesc": "",
    "encryptBossId": "b27bb7016e62952e0nR93Nm-EldZ",
    "encryptBrandId": "aef89d264941d5a133N_0tq0Fw~~",
    "encryptJobId": "9bdd2462b548309d1nBz3t6-GFtS",
    "expectId": 0,
    "goldHunter": 0,
    "gps": {
        "latitude": 36.678054,
        "longitude": 117.134278
    },
    "iconFlagList": [],
    "iconWord": "",
    "industry": 100021,
    "isShield": 0,
    "itemId": 117,
    "jobDegree": "大专",
    "jobExperience": "经验不限",
    "jobLabels": [
        "经验不限",
        "大专"
    ],
    "jobName": "实施工程师",
    "jobType": 0,
    "jobValidStatus": 1,
    "leastMonthDesc": "",
    "lid": "8YXomAzUaon.search.117",
    "optimal": 0,
    "outland": 0,
    "proxyJob": 0,
    "proxyType": 0,
    "salaryDesc": "6-11K",
    "securityId": "4Lh4ewJkmPDw9-f10ddB65bRbr8rty1iplDFV7U9HvG_L7w76CO5nzhy3nUGp4tL7I2_oEqR1KmKCqjvMOVzdS8AePj9qeEJjezyZ7OUIHW1SEZEfVg~",
    "showTopPosition": false,
    "skills": [
        "软件实施",
        "实施工程师/顾问"
    ],
    "welfareList": [
        "带薪年假",
        "五险一金",
        "员工旅游",
        "节日福利",
        "生日福利",
        "定期体检",
        "年终奖"
    ]
}