{
    "afterNameIcons": [],
    "anonymous": 0,
    "areaDistrict": "江汉区",
    "atsDirectPost": false,
    "beforeNameIcons": [],
    "bossAvatar": "https://img.bosszhipin.com/beijin/upload/avatar/20250108/607f1f3d68754fd0cdf4d4a24577063a51357e1b786a5e1dfab6e384085ca819ba8976e7e4f5b68e_s.jpg.webp",
    "bossCert": 3,
    "bossName": "陈佳丽",
    "bossOnline": false,
    "bossTitle": "人事经理",
    "brandIndustry": "广告/公关/会展",
    "brandLogo": "https://img.bosszhipin.com/beijin/upload/com/logo/20230718/7b5b554d84f9729c6b8309413ac1648785dc009ff91b62b6fab6e384085ca819ba8976e7e4f5b68e.jpg",
    "brandName": "拾美文化",
    "brandScaleName": "20-99人",
    "brandStageName": "未融资",
    "businessDistrict": "常青",
    "city": 101200100,
    "cityName": "武汉",
    "contact": false,
    "daysPerWeekDesc": "",
    "encryptBossId": "bbd99ff73c85a9040nN909-0FFtU",
    "encryptBrandId": "2e304ce47264eea51nd83dm_FlM~",
    "encryptJobId": "061a888da8c5037c1Hd83t6_F1BX",
    "expectId": 1077417861,
    "goldHunter": 0,
    "gps": {
        "latitude": 30.60373,
        "longitude": 114.260123
    },
    "iconFlagList": [],
    "iconWord": "",
    "industry": 100101,
    "isShield": 0,
    "itemId": 135,
    "jobDegree": "大专",
    "jobExperience": "1-3年",
    "jobLabels": [
        "1-3年",
        "大专"
    ],
    "jobName": "人事专员 双休加年终奖",
    "jobType": 0,
    "jobValidStatus": 1,
    "leastMonthDesc": "",
    "lid": "1VCAVQLkJ2a.search.135",
    "optimal": 0,
    "outland": 0,
    "proxyJob": 0,
    "proxyType": 0,
    "salaryDesc": "4-6K·13薪",
    "securityId": "EAg191Vky2TUy-21MhuvcWR8QAlvny-TWsB5byjkC-xW9X1jJok2djifH6thLbJXJ2tE9HeiER16zkPKWZ_tCMdet4U5tFlSs7zbRuZ_yZiFvERDaib7oJw3yLT-nPMmame4UDP3knunWFA~",
    "showTopPosition": false,
    "skills": [
        "培训实施",
        "企业文化建设",
        "招聘与配置"
    ],
    "welfareList": [
        "餐补",
        "带薪年假",
        "年终奖",
        "交通补助",
        "全勤奖",
        "团建聚餐",
        "节日福利",
        "生日福利",
        "保底工资",
        "底薪加提成",
        "员工旅游",
        "定期体检",
        "双亲慰问金",
        "绩效奖金",
        "工龄奖",
        "住房补贴",
        "通讯补贴",
        "五险一金",
        "零食下午茶",
        "有无线网"
    ]
}