{
    "anonymous": 0,
    "areaDistrict": "浦东新区",
    "atsDirectPost": false,
    "bossAvatar": "https://img.bosszhipin.com/beijin/upload/avatar/20240604/607f1f3d68754fd0873582fe20218cf18178028a1001f32fe5ae8d5910684457b5f8db06cb36f647_s.png.webp",
    "bossCert": 3,
    "bossName": "柴利利",
    "bossOnline": false,
    "bossTitle": "招聘",
    "brandIndustry": "其他生活服务",
    "brandLogo": "https://img.bosszhipin.com/beijin/app/mobile/normal-0e3f1e4441a21d4874cece3a3d81f0fe.png",
    "brandName": "厦门好慷家政服务",
    "brandScaleName": "10000人以上",
    "brandStageName": "",
    "businessDistrict": "康桥",
    "city": 101020100,
    "cityName": "上海",
    "contact": false,
    "daysPerWeekDesc": "",
    "encryptBossId": "fbea98018b3b60660nNz3dW5FVZU",
    "encryptBrandId": "25ef93abbe57488603J929W6FQ~~",
    "encryptJobId": "1e689cad221e8ad61HJ53NS1GFdV",
    "expectId": 974537683,
    "goldHunter": 0,
    "gps": null,
    "iconFlagList": [],
    "iconWord": "",
    "industry": 101106,
    "isShield": 0,
    "itemId": 300,
    "jobDegree": "本科",
    "jobExperience": "1-3年",
    "jobLabels": [
        "1-3年",
        "本科"
    ],
    "jobName": "经营分析师",
    "jobType": 0,
    "jobValidStatus": 1,
    "leastMonthDesc": "",
    "lid": "7vWvNoCMFvX.search.300",
    "optimal": 0,
    "outland": 0,
    "proxyJob": 0,
    "proxyType": 0,
    "salaryDesc": "7-10K",
    "securityId": "nKqXx0DRb4reK-p1EOIWrrm7gamXDdFMimMzVyV72vB0piYWqKzxlwoVn1IgDp825sJ_8PSUM2vcHCHyz-fzhoqjG6tjjKgsY7FkTHkxQWRBClHYMHEW1ky3HOW8ZLEVlfsaVTKc1Jpj",
    "showTopPosition": false,
    "skills": [
        "数据分析/挖掘经验",
        "业务运营",
        "财务基础"
    ],
    "welfareList": [
        "节日福利",
        "加班补助",
        "生日福利",
        "工龄奖",
        "绩效奖金",
        "团建聚餐",
        "年终奖"
    ]
}