{
    "anonymous": 0,
    "areaDistrict": "蜀山区",
    "atsDirectPost": false,
    "bossAvatar": "https://img.bosszhipin.com/beijin/upload/avatar/20230823/607f1f3d68754fd05b4f398d8888b50bbb238e0d5527fe059f8c8e7f7c8280893ad02127b2b1c203_s.jpg.webp",
    "bossCert": 3,
    "bossName": "王先生",
    "bossOnline": true,
    "bossTitle": "区域招聘经理",
    "brandIndustry": "医疗健康",
    "brandLogo": "https://img.bosszhipin.com/beijin/mcs/banner/930a685836e56d344cade18e62176d43cfcd208495d565ef66e7dff9f98764da.png",
    "brandName": "爱康集团",
    "brandScaleName": "10000人以上",
    "brandStageName": "未融资",
    "businessDistrict": "二环路",
    "city": 101220100,
    "cityName": "合肥",
    "contact": false,
    "daysPerWeekDesc": "",
    "encryptBossId": "daa6e0665259c68d1nVz29q-EVtU",
    "encryptBrandId": "4306064ef1c1c6771nB-3Ni0",
    "encryptJobId": "aee4f527ed6868df1HN829m9FlBQ",
    "expectId": 0,
    "goldHunter": 0,
    "gps": null,
    "iconFlagList": [],
    "iconWord": "",
    "industry": 100006,
    "isShield": 0,
    "itemId": 200,
    "jobDegree": "大专",
    "jobExperience": "1-3年",
    "jobLabels": [
        "1-3年",
        "大专"
    ],
    "jobName": "技术支持工程师",
    "jobType": 0,
    "jobValidStatus": 1,
    "leastMonthDesc": "",
    "lid": "5ehOHzIcff9.search.200",
    "optimal": 0,
    "outland": 0,
    "proxyJob": 0,
    "proxyType": 0,
    "salaryDesc": "4-6K",
    "securityId": "SzIAXlXAywtej-41ZUvN_ANNZ6lnmBCsyuuckc9QBcacD6YpI3fepYJZHVEs7eQG4mFZExTwiGlScG5lG_Uhs9OaAatVhdb9w6COP0NceKjXTx8MsZ1BUFQfuksMkGArP_53694l2_eu4C8A3yR12g~~",
    "showTopPosition": false,
    "skills": [
        "企业内部IT技术支持",
        "计算机/通信相关专业"
    ],
    "welfareList": [
        "五险一金",
        "年度员工体检",
        "定期体检",
        "节日福利",
        "交通补助",
        "零食下午茶",
        "员工旅游",
        "带薪年假"
    ]
}