{
    "anonymous": 0,
    "areaDistrict": "武侯区",
    "atsDirectPost": false,
    "bossAvatar": "https://img.bosszhipin.com/beijin/upload/avatar/20220715/607f1f3d68754fd0dadce54572ece762a561bc61f78ced6f6c6855479d252492df4cc83b7e79d957_s.jpg",
    "bossCert": 3,
    "bossName": "赵女士",
    "bossOnline": false,
    "bossTitle": "测试",
    "brandIndustry": "互联网",
    "brandLogo": "https://zhengxin-pub.cdn.bcebos.com/logopic/76bd483540083e534a88798c5347cf7c_fullsize.jpg",
    "brandName": "巨网云",
    "brandScaleName": "20-99人",
    "brandStageName": "不需要融资",
    "businessDistrict": "新会展中心",
    "city": 101270100,
    "cityName": "成都",
    "contact": false,
    "daysPerWeekDesc": "",
    "encryptBossId": "3167a1287b244c210nF62Nq9GVNW",
    "encryptBrandId": "7a9ef8b82a17eaad1HN829S-",
    "encryptJobId": "5a80e4e88ec1e19c1Xd82dy9FVBS",
    "expectId": 0,
    "goldHunter": 0,
    "gps": null,
    "iconFlagList": [],
    "iconWord": "",
    "industry": 100020,
    "isShield": 0,
    "itemId": 131,
    "jobDegree": "本科",
    "jobExperience": "1-3年",
    "jobLabels": [
        "1-3年",
        "本科"
    ],
    "jobName": "初级测试工程师",
    "jobType": 0,
    "jobValidStatus": 1,
    "leastMonthDesc": "",
    "lid": "9AIONFaMCw5.search.131",
    "optimal": 0,
    "outland": 0,
    "proxyJob": 0,
    "proxyType": 0,
    "salaryDesc": "3-6K",
    "securityId": "PYZyfe71mf7RL-l1s1jxTqEIBvqQqBROnTiVFYW25YCA1ZqqKp3rqHHMKRS6OKPjAlh8WN6gnOTdg8lIWhneNf4Hg3W8Xag5RS2FAfM5V_5eEINLQw~~",
    "showTopPosition": false,
    "skills": [
        "软件测试"
    ],
    "welfareList": [
        "节日福利",
        "带薪年假",
        "股票期权",
        "团建聚餐",
        "年终奖",
        "零食下午茶",
        "免费工装",
        "五险一金"
    ]
}