{
    "anonymous": 0,
    "areaDistrict": "番禺区",
    "atsDirectPost": false,
    "bossAvatar": "https://img.bosszhipin.com/boss/avatar/avatar_1.png",
    "bossCert": 3,
    "bossName": "冯女士",
    "bossOnline": false,
    "bossTitle": "人事",
    "brandIndustry": "移动互联网",
    "brandLogo": "https://img.bosszhipin.com/beijin/mcs/chatphoto/20180717/7070fe1cfc165cd382f39b4896f93c9fcfcd208495d565ef66e7dff9f98764da.jpg",
    "brandName": "广州宏视",
    "brandScaleName": "100-499人",
    "brandStageName": "未融资",
    "businessDistrict": "华南",
    "city": 101280100,
    "cityName": "广州",
    "contact": false,
    "daysPerWeekDesc": "",
    "encryptBossId": "f8e5eaeebb36b87f0nB62Nu9E1Y~",
    "encryptBrandId": "c2c186b13602161f1Xd-39S8FQ~~",
    "encryptJobId": "1e63be2a3e9f21f11HZ90tm4GFpR",
    "expectId": 0,
    "goldHunter": 0,
    "gps": null,
    "iconFlagList": [],
    "iconWord": "",
    "industry": 100019,
    "isShield": 0,
    "itemId": 236,
    "jobDegree": "本科",
    "jobExperience": "1-3年",
    "jobLabels": [
        "1-3年",
        "本科"
    ],
    "jobName": "海外技术支持",
    "jobType": 0,
    "jobValidStatus": 1,
    "leastMonthDesc": "",
    "lid": "9plnJnSmmcw.search.236",
    "optimal": 0,
    "outland": 0,
    "proxyJob": 0,
    "proxyType": 0,
    "salaryDesc": "5-7K",
    "securityId": "p3DctSRSLAJkE-i1nmSP13FwxxMKflCLWv61jWf-45HrIUa4-J0boPErklWnnNZbvs2Uy7KyL-PFi9qbfIemxu6bw6jw8KMgoOdcnXvsHm0Qjado2Q~~",
    "showTopPosition": false,
    "skills": [
        "售后支持/客户响应经验",
        "英文可沟通",
        "计算机/通信相关专业"
    ],
    "welfareList": [
        "生日派对",
        "上班时间",
        "节日福利",
        "零食下午茶",
        "五险一金",
        "年终奖",
        "定期体检",
        "90后团队",
        "员工旅游",
        "绩效奖金",
        "带薪年假",
        "餐补",
        "加班补助",
        "领导nice"
    ]
}