{
    "anonymous": 0,
    "areaDistrict": "市中区",
    "atsDirectPost": false,
    "bossAvatar": "https://img.bosszhipin.com/beijin/upload/avatar/20201104/7485cc6e91845a3a859fc4bc5d0ceb73513396e910322f24fc705e61b04a5cba_s.jpg",
    "bossCert": 3,
    "bossName": "陈女士",
    "bossOnline": false,
    "bossTitle": "人事主管",
    "brandIndustry": "电力/热力/燃气/水利",
    "brandLogo": "https://img.bosszhipin.com/beijin/mcs/chatphoto/20210414/83eca84cc10358e76799f21bd4b90f12513396e910322f24fc705e61b04a5cba_s.jpg",
    "brandName": "秋淇分析",
    "brandScaleName": "20-99人",
    "brandStageName": "未融资",
    "businessDistrict": "舜耕路",
    "city": 101120100,
    "cityName": "济南",
    "contact": false,
    "daysPerWeekDesc": "",
    "encryptBossId": "00f3b350c08828ac0Hx63Nu6FlY~",
    "encryptBrandId": "5074e8b61e4dcd453nB82N6-Ew~~",
    "encryptJobId": "e89ac4f771dcd9081nZ639i8GFVY",
    "expectId": 0,
    "goldHunter": 0,
    "gps": {
        "latitude": 36.598831,
        "longitude": 117.011277
    },
    "iconFlagList": [],
    "iconWord": "",
    "industry": 101205,
    "isShield": 0,
    "itemId": 188,
    "jobDegree": "大专",
    "jobExperience": "1-3年",
    "jobLabels": [
        "1-3年",
        "大专"
    ],
    "jobName": "实施工程师",
    "jobType": 0,
    "jobValidStatus": 1,
    "leastMonthDesc": "",
    "lid": "5KY3XiHitCq.search.188",
    "optimal": 0,
    "outland": 0,
    "proxyJob": 0,
    "proxyType": 0,
    "salaryDesc": "6-8K",
    "securityId": "D7BHnAp98J3oz-q1ntmATN5cvvcPCaK5DfXwTP4rFhGYg4T7Ra7U5q-b1vLypQgOxYD5RTKt6kvQU0Cpr5e5uZf4h5Kr4ZwCrUJSP9SbPfSLlKPJ9w~~",
    "showTopPosition": false,
    "skills": [
        "实施工程师/顾问",
        "安装工程师"
    ],
    "welfareList": [
        "交通补助",
        "餐补",
        "通讯补贴",
        "双休",
        "五险一金"
    ]
}