{
    "anonymous": 0,
    "areaDistrict": "",
    "atsDirectPost": false,
    "bossAvatar": "https://img.bosszhipin.com/beijin/upload/avatar/20240827/607f1f3d68754fd0694911f371ba0a8114bf8911df9c9f21ef811205f833893534a0db40a948dc59_s.png.webp",
    "bossCert": 3,
    "bossName": "王先生",
    "bossOnline": false,
    "bossTitle": "招聘者",
    "brandIndustry": "其他行业",
    "brandLogo": "https://img.bosszhipin.com/beijin/icon/894ce6fa7e58d64d57e7f22d2f3a9d18afa7fcceaa24b8ea28f56f1bb14732c0.png",
    "brandName": "海棠机器人",
    "brandScaleName": "20-99人",
    "brandStageName": "未融资",
    "businessDistrict": "",
    "city": 101281100,
    "cityName": "江门",
    "contact": false,
    "daysPerWeekDesc": "",
    "encryptBossId": "b51072f50dc867891nZ709i-ElVV",
    "encryptBrandId": "cf6ce106c4886ae41XV829-9F1c~",
    "encryptJobId": "0286700a2870fb241Hxy3NS9FlNQ",
    "expectId": 0,
    "goldHunter": 0,
    "gps": {
        "latitude": 22.604103,
        "longitude": 112.839806
    },
    "iconFlagList": [],
    "iconWord": "",
    "industry": 101304,
    "isShield": 0,
    "itemId": 253,
    "jobDegree": "本科",
    "jobExperience": "1-3年",
    "jobLabels": [
        "1-3年",
        "本科"
    ],
    "jobName": "机器人系统测试工程师",
    "jobType": 0,
    "jobValidStatus": 1,
    "leastMonthDesc": "",
    "lid": "abPG8EkJVEd.search.253",
    "optimal": 0,
    "outland": 0,
    "proxyJob": 0,
    "proxyType": 0,
    "salaryDesc": "7-8K",
    "securityId": "PYkFqJZNWZq70-q13hYUI8l6FeryJVqKLKw4UX6OZ6meECm7e2jZAVrmj4L6nBiWpf_K2_xKbhCvKNbr6ZNiSFAYR01YBfN9X7uuiUZ0xE4Y2EUtSP_x",
    "showTopPosition": false,
    "skills": [
        "自动化测试经验",
        "测试工作经验",
        "通信相关专业",
        "性能测试",
        "压力测试",
        "功能测试"
    ],
    "welfareList": [
        "餐补",
        "团建聚餐",
        "零食下午茶"
    ]
}