{
    "anonymous": 0,
    "areaDistrict": "天心区",
    "atsDirectPost": false,
    "bossAvatar": "https://img.bosszhipin.com/boss/avatar/avatar_7.png",
    "bossCert": 3,
    "bossName": "刘棋林",
    "bossOnline": false,
    "bossTitle": "hr",
    "brandIndustry": "计算机软件",
    "brandLogo": "https://img.bosszhipin.com/beijin/mcs/chatphoto/20190821/fc519bde734d597ffcb1f6163ac4fae914e07487184fbe0504af6c0f3936f2b7_s.jpg",
    "brandName": "湖南大唐先一",
    "brandScaleName": "500-999人",
    "brandStageName": "未融资",
    "businessDistrict": "省政府",
    "city": 101250100,
    "cityName": "长沙",
    "contact": false,
    "daysPerWeekDesc": "",
    "encryptBossId": "1d89364e34e8dae00nR-3NW6GFdV",
    "encryptBrandId": "6bb3df921ae65db11nN82Nu-FQ~~",
    "encryptJobId": "70a14fd7ae2d72f31nFy0tW5GFpR",
    "expectId": 1014042683,
    "goldHunter": 0,
    "gps": {
        "latitude": 28.094518,
        "longitude": 112.973773
    },
    "iconFlagList": [],
    "iconWord": "",
    "industry": 100021,
    "isShield": 0,
    "itemId": 247,
    "jobDegree": "本科",
    "jobExperience": "1-3年",
    "jobLabels": [
        "1-3年",
        "本科"
    ],
    "jobName": "C++开发工程师",
    "jobType": 0,
    "jobValidStatus": 1,
    "leastMonthDesc": "",
    "lid": "9zs5udPOxhu.search.247",
    "optimal": 0,
    "outland": 0,
    "proxyJob": 0,
    "proxyType": 0,
    "salaryDesc": "9-14K",
    "securityId": "kEwW1FvnaK9Lh-11hVIp-jbs1Mt2fPeVJquoDf0ABFp8WYXTH0HkBDNwg-_Ze9x9wTmrprHPpceOP6ilGbzLy48UA-J7i_H6Bka6VoWOgIXJbJD9l3bMpKWfwlKNLajRPW4jyX8mgkqpZg~~",
    "showTopPosition": false,
    "skills": [
        "Shell",
        "数据结构",
        "多线程",
        "网络协议",
        "网络编程",
        "分布式技术",
        "Windows",
        "架构师"
    ],
    "welfareList": [
        "带薪年假",
        "通讯补贴",
        "节日福利",
        "工会活动",
        "年终奖",
        "餐补",
        "五险一金",
        "包吃",
        "定期体检"
    ]
}