{
    "anonymous": 0,
    "areaDistrict": "黄埔区",
    "atsDirectPost": false,
    "bossAvatar": "https://img.bosszhipin.com/beijin/mcs/useravatar/20180427/0c14487ad602d34a03dbecf5e0e15033cfcd208495d565ef66e7dff9f98764da_s.jpg",
    "bossCert": 3,
    "bossName": "孙女士",
    "bossOnline": true,
    "bossTitle": "HR",
    "brandIndustry": "计算机软件",
    "brandLogo": "https://img.bosszhipin.com/beijin/upload/com/workfeel/20210722/270509fa82dd4e7a6e1cea4e38c6bb455b5d53c8d16eb634483c07a2a1294204.jpg",
    "brandName": "神州信息",
    "brandScaleName": "10000人以上",
    "brandStageName": "已上市",
    "businessDistrict": "大沙",
    "city": 101280100,
    "cityName": "广州",
    "contact": false,
    "daysPerWeekDesc": "",
    "encryptBossId": "eeb87ff3704d38bb1Hx62d64FVA~",
    "encryptBrandId": "77b49621ee4cae601Xdz2di0EFc~",
    "encryptJobId": "be91fd5ed45f455e1HN929q7GVFU",
    "expectId": 1014042683,
    "goldHunter": 0,
    "gps": null,
    "iconFlagList": [],
    "iconWord": "",
    "industry": 100021,
    "isShield": 0,
    "itemId": 52,
    "jobDegree": "本科",
    "jobExperience": "1-3年",
    "jobLabels": [
        "1-3年",
        "本科"
    ],
    "jobName": "Java开发 银行",
    "jobType": 0,
    "jobValidStatus": 1,
    "leastMonthDesc": "",
    "lid": "1rncpOBjXXf.search.52",
    "optimal": 0,
    "outland": 0,
    "proxyJob": 0,
    "proxyType": 0,
    "salaryDesc": "10-11K",
    "securityId": "UugK0JvqvpAx9-J106yzY7299CPCdcmT9BnmD6yaRVjrndvs6HdCoTdlAc2Wa8tJMhu3MqBPS968EEtVctBhSEduUGqkVSGnSB48GBYOGsItWWvKf16Ez2cjAGovoLQSB7P7o5pKMCm_4uvawav29BZ8_YcCszec70NF3icnH3IiTOLCwQ~~",
    "showTopPosition": false,
    "skills": [
        "Java",
        "Spring",
        "MySQL"
    ],
    "welfareList": [
        "带薪年假",
        "定期体检",
        "年终奖",
        "补充医疗保险",
        "朝九晚六",
        "餐补",
        "五险一金",
        "意外险",
        "股票期权"
    ]
}