{
    "anonymous": 0,
    "areaDistrict": "樊城区",
    "atsDirectPost": false,
    "bossAvatar": "https://img.bosszhipin.com/beijin/upload/avatar/20240918/607f1f3d68754fd0ce17ebaaf1839b354c842153406c19f7dc75988f8b9d849d80d4ed2edc21d703_s.jpg.webp",
    "bossCert": 3,
    "bossName": "朱女士",
    "bossOnline": true,
    "bossTitle": "招聘专员",
    "brandIndustry": "企业服务",
    "brandLogo": "https://img.bosszhipin.com/beijin/upload/com/workfeel/20240821/7bf6f160950405e9c2c9b1b1a28ee5f379860e8907acc97f93d07e994011c2ac20cf151fb77ba3a2.png.webp",
    "brandName": "金慧科技",
    "brandScaleName": "100-499人",
    "brandStageName": "",
    "businessDistrict": "新五中",
    "city": 101200200,
    "cityName": "襄阳",
    "contact": false,
    "daysPerWeekDesc": "",
    "encryptBossId": "c27eb99a660950a50nF-3NS5GVBT",
    "encryptBrandId": "50415811e3d672e503182tu9FA~~",
    "encryptJobId": "746e987d92bd6ce51HR639q7GVRX",
    "expectId": 0,
    "goldHunter": 0,
    "gps": null,
    "iconFlagList": [],
    "iconWord": "",
    "industry": 100015,
    "isShield": 0,
    "itemId": 230,
    "jobDegree": "大专",
    "jobExperience": "经验不限",
    "jobLabels": [
        "经验不限",
        "大专"
    ],
    "jobName": "数据标注",
    "jobType": 0,
    "jobValidStatus": 1,
    "leastMonthDesc": "",
    "lid": "4BaaunU5NXe.search.230",
    "optimal": 0,
    "outland": 0,
    "proxyJob": 0,
    "proxyType": 0,
    "salaryDesc": "3-4K",
    "securityId": "to2ullAwoX1tw-O1Cm24-sqd3ZIJXPtPOATrPnzX-Arq-xNEs1K33V09JCfzPHvV9svqCHaB7plZNArke5nEms8JBO45TVAk0Zbuecn8W8ydEiSlaFcSng1P7OgW6yiDPpHY5lHdtNvGQCxlWb0nGH4~",
    "showTopPosition": false,
    "skills": [
        "数据标注",
        "文本标注",
        "视频标注",
        "早九晚六、月休八天、五险一金",
        "图片标注",
        "分类标注"
    ],
    "welfareList": [
        "五险一金",
        "底薪加提成",
        "零食下午茶",
        "全勤奖",
        "工龄奖",
        "夜班补助",
        "保底工资",
        "意外险",
        "加班补助",
        "法定节假日三薪",
        "生日福利",
        "绩效奖金",
        "包住",
        "宿舍有空调"
    ]
}