{
    "afterNameIcons": [],
    "anonymous": 0,
    "areaDistrict": "岳麓区",
    "atsDirectPost": false,
    "beforeNameIcons": [],
    "bossAvatar": "https://img.bosszhipin.com/beijin/upload/avatar/20211008/607f1f3d68754fd094a5c2d02b5081bf3c3a7635016a8f949c0ada643ccc46baacb838dd3b80c0e2_s.jpg",
    "bossCert": 3,
    "bossName": "张瀚文",
    "bossOnline": false,
    "bossTitle": "HR",
    "brandIndustry": "互联网",
    "brandLogo": "https://img.bosszhipin.com/beijin/mcs/chatphoto/20191030/711f6a3881e2e91bf31fb40a16f7a959f10117fcc14e8ce5055796d43b6f5a8e_s.jpg",
    "brandName": "云畅科技",
    "brandScaleName": "20-99人",
    "brandStageName": "不需要融资",
    "businessDistrict": "含浦",
    "city": 101250100,
    "cityName": "长沙",
    "contact": false,
    "daysPerWeekDesc": "",
    "encryptBossId": "aa8288a35fa3c87b1nR539--E1JQ",
    "encryptBrandId": "c40898c7ca04789203x-3dy6",
    "encryptJobId": "6ec00ba459050f931H182tu6GFFW",
    "expectId": 0,
    "goldHunter": 0,
    "gps": {
        "latitude": 28.130749,
        "longitude": 112.948829
    },
    "iconFlagList": [],
    "iconWord": "",
    "industry": 100020,
    "isShield": 0,
    "itemId": 59,
    "jobDegree": "本科",
    "jobExperience": "1-3年",
    "jobLabels": [
        "1-3年",
        "本科"
    ],
    "jobName": "测试工程师",
    "jobType": 0,
    "jobValidStatus": 1,
    "leastMonthDesc": "",
    "lid": "3tN0IWHrnRg.search.59",
    "optimal": 0,
    "outland": 0,
    "proxyJob": 0,
    "proxyType": 0,
    "salaryDesc": "7-9K",
    "securityId": "W8jAKYFeltXGW-d1mIENvpgOSIiRhcso75Hd_2Vww0PoPm7-O8XyqNrhlKFi4n5kic8-vhBl-aquiPh-EjNk-i6u7EYL8enBaABK9-Qy9yj207TH5g~~",
    "showTopPosition": false,
    "skills": [
        "测试工作经验",
        "通信相关专业",
        "性能测试",
        "功能测试",
        "计算机相关专业"
    ],
    "welfareList": [
        "员工旅游",
        "餐补",
        "股票期权",
        "带薪年假",
        "五险一金",
        "交通补助",
        "年终奖",
        "绩效奖金"
    ]
}