{
    "anonymous": 0,
    "areaDistrict": "顺德区",
    "atsDirectPost": false,
    "bossAvatar": "https://img.bosszhipin.com/boss/avatar/avatar_2.png",
    "bossCert": 3,
    "bossName": "黄女士",
    "bossOnline": false,
    "bossTitle": "HR",
    "brandIndustry": "家具/家电/家居",
    "brandLogo": "https://img.bosszhipin.com/beijin/upload/com/logo/20200222/b114c9e83fa06aef94d68a77dd3b329e513385799a4705e6f718a8b5439497f8.jpg",
    "brandName": "美的",
    "brandScaleName": "10000人以上",
    "brandStageName": "已上市",
    "businessDistrict": "北滘",
    "city": 101280800,
    "cityName": "佛山",
    "contact": false,
    "daysPerWeekDesc": "",
    "encryptBossId": "e047c3473a3418b83nF42du5E1M~",
    "encryptBrandId": "cada161dd8f3cc8f1nF93dy1FA~~",
    "encryptJobId": "735c59d821ff64ce1XJy29S6GVpY",
    "expectId": 0,
    "goldHunter": 0,
    "gps": null,
    "iconFlagList": [],
    "iconWord": "",
    "industry": 101004,
    "isShield": 0,
    "itemId": 193,
    "jobDegree": "本科",
    "jobExperience": "1-3年",
    "jobLabels": [
        "1-3年",
        "本科"
    ],
    "jobName": "整机测试工程师",
    "jobType": 0,
    "jobValidStatus": 1,
    "leastMonthDesc": "",
    "lid": "120AIyiO1nI.search.193",
    "optimal": 0,
    "outland": 0,
    "proxyJob": 0,
    "proxyType": 0,
    "salaryDesc": "5-6K·13薪",
    "securityId": "XjHtDouaiZcfR-B1nSrAeh5ujcbui9GsygiAKldtldlBrazDgwfSUjAg-TttpI9IlmeYJiZVy90hxnDkspK9VIq9L0jJhaDPAIuWJzvq9lPnK6EKhw~~",
    "showTopPosition": false,
    "skills": [
        "功能测试",
        "测试工作经验"
    ],
    "welfareList": [
        "员工旅游",
        "零食下午茶",
        "交通补助",
        "住房补贴",
        "全勤奖",
        "免费班车",
        "五险一金",
        "餐补",
        "定期体检",
        "加班补助",
        "通讯补贴",
        "补充医疗保险",
        "节日福利",
        "带薪年假",
        "年终奖"
    ]
}