{
    "anonymous": 0,
    "areaDistrict": "鼓楼区",
    "atsDirectPost": false,
    "bossAvatar": "https://img.bosszhipin.com/beijin/upload/avatar/20240213/607f1f3d68754fd05304e0f11f012d6b4ee89fc9cbe0c79ac3352829b9318b9b9b71ac354282c0e0_s.png.webp",
    "bossCert": 3,
    "bossName": "马先生",
    "bossOnline": false,
    "bossTitle": "创始人",
    "brandIndustry": "电子商务",
    "brandLogo": "https://img.bosszhipin.com/beijin/app/mobile/normal-0e3f1e4441a21d4874cece3a3d81f0fe.png",
    "brandName": "店立达软件",
    "brandScaleName": "0-20人",
    "brandStageName": "不需要融资",
    "businessDistrict": "定淮门",
    "city": 101190100,
    "cityName": "南京",
    "contact": false,
    "daysPerWeekDesc": "",
    "encryptBossId": "0d45e82225376a011nV83t2_ElE~",
    "encryptBrandId": "5fda1714c3b575201X1_3tq-",
    "encryptJobId": "87fd709f128569d61Hd639u0E1NT",
    "expectId": 0,
    "goldHunter": 0,
    "gps": {
        "latitude": 32.072397,
        "longitude": 118.75308
    },
    "iconFlagList": [],
    "iconWord": "",
    "industry": 100001,
    "isShield": 0,
    "itemId": 61,
    "jobDegree": "大专",
    "jobExperience": "1-3年",
    "jobLabels": [
        "1-3年",
        "大专"
    ],
    "jobName": "saas软件售前售后技术支持",
    "jobType": 0,
    "jobValidStatus": 1,
    "leastMonthDesc": "",
    "lid": "7TGs7n5t6ob.search.61",
    "optimal": 0,
    "outland": 0,
    "proxyJob": 0,
    "proxyType": 0,
    "salaryDesc": "4-8K",
    "securityId": "7ZK5KvU4kcRFX-l1ku-HLz9Ao-NoPV41_WojIDWniAFEB10kfBgIW06W51TWnxqDMU64il2y8EW5kMaY_6dfGIyLBaB-kMVqsuVWmnFgJzKp0z_y",
    "showTopPosition": false,
    "skills": [
        "ERP/OA/CRM系统",
        "其他类型SaaS/PaaS",
        "软件技术支持经验",
        "软件实施经验"
    ],
    "welfareList": []
}