{
    "anonymous": 0,
    "areaDistrict": "南海区",
    "atsDirectPost": false,
    "bossAvatar": "https://img.bosszhipin.com/boss/avatar/avatar_10.png",
    "bossCert": 3,
    "bossName": "邹女士",
    "bossOnline": false,
    "bossTitle": "人事专员",
    "brandIndustry": "电气机械/器材",
    "brandLogo": "https://img.bosszhipin.com/beijin/mcs/chatphoto/20200717/2f2d3aebddda0bb67fccb1c3b66dbecd6a0da8dd4427bb38d9ead72ab93dccba_s.jpg",
    "brandName": "天富科技",
    "brandScaleName": "100-499人",
    "brandStageName": "未融资",
    "businessDistrict": "狮山",
    "city": 101280800,
    "cityName": "佛山",
    "contact": false,
    "daysPerWeekDesc": "",
    "encryptBossId": "2e5ba95c062484da0X1729i1F1Q~",
    "encryptBrandId": "e3e9ce3cf5b3e80e3ndz3t-9EA~~",
    "encryptJobId": "fb0d5bf670ab60e41XN-3NW8FlZW",
    "expectId": 0,
    "goldHunter": 0,
    "gps": {
        "latitude": 23.150557,
        "longitude": 113.025369
    },
    "iconFlagList": [],
    "iconWord": "",
    "industry": 100908,
    "isShield": 0,
    "itemId": 144,
    "jobDegree": "大专",
    "jobExperience": "经验不限",
    "jobLabels": [
        "经验不限",
        "大专"
    ],
    "jobName": "实施工程师",
    "jobType": 0,
    "jobValidStatus": 1,
    "leastMonthDesc": "",
    "lid": "9raN7aqyEU9.search.144",
    "optimal": 0,
    "outland": 0,
    "proxyJob": 0,
    "proxyType": 0,
    "salaryDesc": "4-6K",
    "securityId": "R8byupQCMJDDC-E1P4G9eiLjk4I8fyodL82xUVJsZwIBq7MN9Ctcfi5agsyah1B_tmjvyNNchoiKTP5qhtd3Qdpu1CFKhvanB0x5lCPSsbzdyZFMSQ~~",
    "showTopPosition": false,
    "skills": [
        "ERP"
    ],
    "welfareList": [
        "员工旅游",
        "通讯补贴",
        "加班补助",
        "股票期权",
        "宿舍有空调",
        "高温补贴",
        "全勤奖",
        "年终奖",
        "意外险",
        "节假日加班费",
        "节日福利",
        "工龄奖"
    ]
}