{
    "afterNameIcons": [],
    "anonymous": 0,
    "areaDistrict": "岳麓区",
    "atsDirectPost": false,
    "beforeNameIcons": [],
    "bossAvatar": "https://img.bosszhipin.com/boss/avatar/avatar_15.png",
    "bossCert": 3,
    "bossName": "黄先生",
    "bossOnline": false,
    "bossTitle": "招聘者",
    "brandIndustry": "装修装饰",
    "brandLogo": "https://img.bosszhipin.com/beijin/icon/894ce6fa7e58d64d57e7f22d2f3a9d18afa7fcceaa24b8ea28f56f1bb14732c0.png",
    "brandName": "玄雅华居",
    "brandScaleName": "20-99人",
    "brandStageName": "不需要融资",
    "businessDistrict": "大王山",
    "city": 101250100,
    "cityName": "长沙",
    "contact": false,
    "daysPerWeekDesc": "",
    "encryptBossId": "df78881460c21f0c1nV80ti8EVY~",
    "encryptBrandId": "191753fc30f97c241Hd93t64ElM~",
    "encryptJobId": "ca7731844d2ac1a603V62dm_EVtR",
    "expectId": 0,
    "goldHunter": 0,
    "gps": {
        "latitude": 28.090966,
        "longitude": 112.916267
    },
    "iconFlagList": [],
    "iconWord": "",
    "industry": 100704,
    "isShield": 0,
    "itemId": 265,
    "jobDegree": "大专",
    "jobExperience": "1-3年",
    "jobLabels": [
        "1-3年",
        "大专"
    ],
    "jobName": "家装室内设计师助理",
    "jobType": 0,
    "jobValidStatus": 1,
    "leastMonthDesc": "",
    "lid": "2NBgAMMse3l.search.265",
    "optimal": 0,
    "outland": 0,
    "proxyJob": 0,
    "proxyType": 0,
    "salaryDesc": "1-5K",
    "securityId": "l01JZBEhS1ov6-g1K8-jYW7HHtNCkwEBaWSnYbsFXIpQ0-qpO0OcS3jrYTNK2FfiFKwNVU_e_p8-KPFrb_0m4hMKioDIqmihPIErdSpKMxF2vNeiPHU~",
    "showTopPosition": false,
    "skills": [
        "别墅",
        "普通住宅",
        "AutoCAD",
        "SketchUp",
        "PS",
        "酷家乐",
        "良好的方案沟通能力",
        "独立完成施工图"
    ],
    "welfareList": [
        "年终奖",
        "底薪加提成",
        "绩效奖金",
        "保底工资",
        "节日福利"
    ]
}