{
    "anonymous": 0,
    "areaDistrict": "渝北区",
    "atsDirectPost": false,
    "bossAvatar": "https://img.bosszhipin.com/beijin/upload/avatar/20240410/607f1f3d68754fd02fca437fd352680ef644ae2cf3fc20ea830c5b64de0c92f12bae65309b66bf5d_s.jpg.webp",
    "bossCert": 3,
    "bossName": "皂先生",
    "bossOnline": false,
    "bossTitle": "招聘顾问",
    "brandIndustry": "计算机软件",
    "brandLogo": "https://img.bosszhipin.com/beijin/mcs/banner/8a1a84f879ebdbd5f0503c49bc0f424ecfcd208495d565ef66e7dff9f98764da.jpg",
    "brandName": "拓保软件",
    "brandScaleName": "1000-9999人",
    "brandStageName": "不需要融资",
    "businessDistrict": "人和",
    "city": 101040100,
    "cityName": "重庆",
    "contact": false,
    "daysPerWeekDesc": "",
    "encryptBossId": "bab82d94033d24ed1HB62ti7",
    "encryptBrandId": "e44063ab762f0e6e1XR60t29",
    "encryptJobId": "d6f041180c6ec2a51HJ93d27FFFU",
    "expectId": 1014042683,
    "goldHunter": 0,
    "gps": null,
    "iconFlagList": [],
    "iconWord": "",
    "industry": 100021,
    "isShield": 0,
    "itemId": 268,
    "jobDegree": "本科",
    "jobExperience": "1-3年",
    "jobLabels": [
        "1-3年",
        "本科"
    ],
    "jobName": "急聘长期稳定-汽车测试-周末双休-线上面试",
    "jobType": 0,
    "jobValidStatus": 1,
    "leastMonthDesc": "",
    "lid": "4xdQiE6IlTD.search.268",
    "optimal": 0,
    "outland": 0,
    "proxyJob": 0,
    "proxyType": 0,
    "salaryDesc": "6-9K",
    "securityId": "aMVS8VfrGJ4RR-w1iHIE9LtifnbdoCmwK_ExoBluoTdw9S-D1cnz77dSxEwSAEBJUpB6bkFqiktFYwGf32FWiZ7FNcU5Xq58urOvhB8i4D-G3KTCEOrEPHQDmVw6b_drtAblATVc",
    "showTopPosition": false,
    "skills": [
        "功能测试"
    ],
    "welfareList": [
        "带薪年假",
        "员工旅游",
        "定期体检",
        "零食下午茶",
        "保底工资",
        "体检",
        "底薪加提成",
        "生日福利",
        "加班补助",
        "绩效奖金",
        "意外险",
        "节日福利",
        "有无线网",
        "年终奖",
        "补充医疗保险",
        "团建旅游",
        "五险一金",
        "餐补",
        "全勤奖"
    ]
}