{
    "anonymous": 0,
    "areaDistrict": "江夏区",
    "atsDirectPost": false,
    "bossAvatar": "https://img.bosszhipin.com/boss/avatar/avatar_7.png",
    "bossCert": 3,
    "bossName": "崔先生",
    "bossOnline": false,
    "bossTitle": "HRCOE",
    "brandIndustry": "互联网",
    "brandLogo": "https://img.bosszhipin.com/beijin/icon/894ce6fa7e58d64d57e7f22d2f3a9d18afa7fcceaa24b8ea28f56f1bb14732c0.png",
    "brandName": "众汇思创",
    "brandScaleName": "0-20人",
    "brandStageName": "",
    "businessDistrict": "流芳",
    "city": 101200100,
    "cityName": "武汉",
    "contact": false,
    "daysPerWeekDesc": "",
    "encryptBossId": "fcd5969cb8f8a6680HZ_2dy_Fw~~",
    "encryptBrandId": "1aa2241e128832241HJ62964EFI~",
    "encryptJobId": "7e56a572f5dd80bf1HN62Ny1FlJY",
    "expectId": 0,
    "goldHunter": 0,
    "gps": null,
    "iconFlagList": [],
    "iconWord": "",
    "industry": 100020,
    "isShield": 0,
    "itemId": 256,
    "jobDegree": "大专",
    "jobExperience": "1-3年",
    "jobLabels": [
        "1-3年",
        "大专"
    ],
    "jobName": "研发工程师",
    "jobType": 0,
    "jobValidStatus": 1,
    "leastMonthDesc": "",
    "lid": "D3LXOK3EBX.search.256",
    "optimal": 0,
    "outland": 0,
    "proxyJob": 0,
    "proxyType": 0,
    "salaryDesc": "8-10K",
    "securityId": "_wMRBnKJvt6CY-_1DP5n-pHUb5iZCruosY6pySHEX6ANTrjP3qCx73ng5-yRzp7TgSpvwE0IARoeW13JTZF-JadnzR3w1M2U01U78Qwq1VpH7vzV0Q~~",
    "showTopPosition": false,
    "skills": [
        "接受居家办公",
        "Java",
        "MySQL",
        "Redis",
        "SQL Server"
    ],
    "welfareList": []
}