{
    "anonymous": 0,
    "areaDistrict": "昌平区",
    "atsDirectPost": false,
    "bossAvatar": "https://img.bosszhipin.com/beijin/upload/avatar/20240802/607f1f3d68754fd05f8418473816a6597d067be8c5cd02efd6eaa2b4c03a2652da0f0162b9d96d13_s.jpg.webp",
    "bossCert": 3,
    "bossName": "李女士",
    "bossOnline": false,
    "bossTitle": "招聘顾问",
    "brandIndustry": "互联网",
    "brandLogo": "https://img.bosszhipin.com/beijin/mcs/banner/55e497a3c749352df771d48a6ed5d279cfcd208495d565ef66e7dff9f98764da.jpg",
    "brandName": "好未来",
    "brandScaleName": "10000人以上",
    "brandStageName": "已上市",
    "businessDistrict": "回龙观",
    "city": 101010100,
    "cityName": "北京",
    "contact": false,
    "daysPerWeekDesc": "",
    "encryptBossId": "59892039e72a4e821nVy3du9ElFZ",
    "encryptBrandId": "efa878c051261c7433Z6",
    "encryptJobId": "c377a7d001b8f5591HN_29q-E1ZQ",
    "expectId": 0,
    "goldHunter": 0,
    "gps": null,
    "iconFlagList": [],
    "iconWord": "",
    "industry": 100020,
    "isShield": 0,
    "itemId": 159,
    "jobDegree": "本科",
    "jobExperience": "1-3年",
    "jobLabels": [
        "1-3年",
        "本科"
    ],
    "jobName": "测试开发工程师",
    "jobType": 0,
    "jobValidStatus": 1,
    "leastMonthDesc": "",
    "lid": "WkIRhNfYI2.search.159",
    "optimal": 0,
    "outland": 0,
    "proxyJob": 0,
    "proxyType": 0,
    "salaryDesc": "20-25K",
    "securityId": "CvsV18VzjI0Qa-01qdnxvdD5lEqKcUbEwIXBSe5MVkHGKsRYs9xVUddPuF5uvw7txmE3f6uzeeK7wHpiIjPfefEnLTWZy8sCGl4iOLxmAHsWRg~~",
    "showTopPosition": false,
    "skills": [
        "Java",
        "Python",
        "C++",
        "计算机相关专业",
        "掌握软件测试理论和流程"
    ],
    "welfareList": [
        "补充医疗保险",
        "五险一金",
        "节日福利",
        "定期体检",
        "不定期培训",
        "全勤奖",
        "购房福利",
        "商业保险",
        "年终奖",
        "带薪年假",
        "餐补"
    ]
}