{
    "anonymous": 0,
    "areaDistrict": "雁塔区",
    "atsDirectPost": false,
    "bossAvatar": "https://img.bosszhipin.com/beijin/mcs/useravatar/20190307/4cd73a36d6e7f3f858866b78bc041a48eaf74521287f8d45d17a5d4c00292984_s.jpg",
    "bossCert": 3,
    "bossName": "齐女士",
    "bossOnline": false,
    "bossTitle": "HR",
    "brandIndustry": "计算机软件",
    "brandLogo": "https://img.bosszhipin.com/beijin/mcs/chatphoto/20180411/814a09ccfe65dd4381197f6bfa1b1d23cfcd208495d565ef66e7dff9f98764da.jpg",
    "brandName": "柯莱特集团",
    "brandScaleName": "1000-9999人",
    "brandStageName": "已上市",
    "businessDistrict": "鱼化寨",
    "city": 101110100,
    "cityName": "西安",
    "contact": false,
    "daysPerWeekDesc": "",
    "encryptBossId": "fa826295d531ef3f0nJ-0965E1Y~",
    "encryptBrandId": "879cece58f6a7e7d1XR929W0",
    "encryptJobId": "ee6d962371204cf71HF93N66FFNX",
    "expectId": 0,
    "goldHunter": 0,
    "gps": {
        "latitude": 34.210788,
        "longitude": 108.842263
    },
    "iconFlagList": [],
    "iconWord": "",
    "industry": 100021,
    "isShield": 0,
    "itemId": 199,
    "jobDegree": "大专",
    "jobExperience": "1-3年",
    "jobLabels": [
        "1-3年",
        "大专"
    ],
    "jobName": "测试（西安+外派百度）",
    "jobType": 0,
    "jobValidStatus": 1,
    "leastMonthDesc": "",
    "lid": "1Bncx1ezZjD.search.199",
    "optimal": 0,
    "outland": 0,
    "proxyJob": 0,
    "proxyType": 0,
    "salaryDesc": "6-8K",
    "securityId": "kKQB10nwWkqsd-l1BwqFDJfegm4prWU3ZhWy1yqne54564BoBjDImH_EvDd_ydE2WftPnCdFBFrm8nVG7mBOMVi-glDbQGmGd4QLMin3e7EtxWAv",
    "showTopPosition": false,
    "skills": [
        "测试工作经验",
        "通信相关专业",
        "Fiddler",
        "功能测试",
        "计算机相关专业",
        "JMeter",
        "Postman"
    ],
    "welfareList": [
        "五险一金",
        "交通补助",
        "节日福利"
    ]
}