{
    "anonymous": 0,
    "areaDistrict": "西城区",
    "atsDirectPost": false,
    "bossAvatar": "https://img.bosszhipin.com/beijin/mcs/useravatar/20190212/0d8127c1fbee36a51311314dea9a4b7c61fed7731855477616bd3f45a7269eb6_s.jpg",
    "bossCert": 3,
    "bossName": "唐女士",
    "bossOnline": false,
    "bossTitle": "人事主管",
    "brandIndustry": "建筑设计",
    "brandLogo": "https://img.bosszhipin.com/beijin/upload/com/logo/20200819/b3d6a0e838f9c7aba61e789c10ce4b000f08a630b86e9da8d54ac4601b382805.jpg",
    "brandName": "北设",
    "brandScaleName": "0-20人",
    "brandStageName": "未融资",
    "businessDistrict": "新街口",
    "city": 101010100,
    "cityName": "北京",
    "contact": false,
    "daysPerWeekDesc": "",
    "encryptBossId": "863f1aa685e717171nZy2Ny9GFA~",
    "encryptBrandId": "fd01b6d8b8474d4b03F439y6EA~~",
    "encryptJobId": "f5eb13da3f46af051nR629q-FltQ",
    "expectId": 0,
    "goldHunter": 0,
    "gps": null,
    "iconFlagList": [],
    "iconWord": "",
    "industry": 100703,
    "isShield": 0,
    "itemId": 250,
    "jobDegree": "本科",
    "jobExperience": "在校/应届",
    "jobLabels": [
        "在校/应届",
        "本科"
    ],
    "jobName": "道路设计工程师助理",
    "jobType": 5,
    "jobValidStatus": 1,
    "leastMonthDesc": "",
    "lid": "2MS76ifSfR8.search.250",
    "optimal": 0,
    "outland": 0,
    "proxyJob": 0,
    "proxyType": 0,
    "salaryDesc": "4-6K·13薪",
    "securityId": "wpQ2a0ny9YTHN-y1_7Fhn7FCsWQvAgmUTjpO2VO2VAw9oyVx0i3nNrXKE5hy2xAtNS1_N2ZAKL-lnpRKGQn3bM4x5zzeBZOw4qiAbhCSl8QsFyNRGQ~~",
    "showTopPosition": false,
    "skills": [
        "道路工程",
        "路桥工程师",
        "市政工程师",
        "建筑设计",
        "CAD",
        "给排水工程师"
    ],
    "welfareList": [
        "餐补",
        "年终奖",
        "带薪年假",
        "住房补贴",
        "五险一金",
        "员工旅游"
    ]
}