{
    "afterNameIcons": [],
    "anonymous": 0,
    "areaDistrict": "雨花台区",
    "atsDirectPost": false,
    "beforeNameIcons": [],
    "bossAvatar": "https://img.bosszhipin.com/beijin/mcs/useravatar/20160629/f6a3973e763c7e9b23b9911435e07382c5b0899d966ac7fa7718522d848d2853_s.jpg",
    "bossCert": 3,
    "bossName": "蒋敏",
    "bossOnline": false,
    "bossTitle": "人事",
    "brandIndustry": "计算机软件",
    "brandLogo": "https://img.bosszhipin.com/beijin/upload/com/workfeel/20240105/7bf6f160950405e9942d24eadf83e49c2bcf5a0ee02c5233c8f2cf3c324512555b260e30ba91ad61.png.webp",
    "brandName": "南昌中展数智科技",
    "brandScaleName": "1000-9999人",
    "brandStageName": "不需要融资",
    "businessDistrict": "安德门",
    "city": 101190100,
    "cityName": "南京",
    "contact": false,
    "daysPerWeekDesc": "",
    "encryptBossId": "b9bd5cbf3b8bea6c1nZ42dy5F1U~",
    "encryptBrandId": "75c09d6a56bb9f711HV_2NW6FlM~",
    "encryptJobId": "87e74a6e7ac0ed9203R-39y1E1BQ",
    "expectId": 1014042683,
    "goldHunter": 0,
    "gps": {
        "latitude": 31.975492,
        "longitude": 118.786175
    },
    "iconFlagList": [],
    "iconWord": "",
    "industry": 100021,
    "isShield": 0,
    "itemId": 101,
    "jobDegree": "本科",
    "jobExperience": "1-3年",
    "jobLabels": [
        "1-3年",
        "本科"
    ],
    "jobName": "数通产品测试",
    "jobType": 0,
    "jobValidStatus": 1,
    "leastMonthDesc": "",
    "lid": "vURsxsmmk4.search.101",
    "optimal": 0,
    "outland": 0,
    "proxyJob": 0,
    "proxyType": 0,
    "salaryDesc": "8-13K",
    "securityId": "2YefKn7BEI9y2-g14-4nHLX83dAcntoEZZKPxum1mM5S1VPl2TkVFsguajXhLHMr19v29ltSjozuqM8tNNXz1laYtu29AsQdlJg-_TjWicypB7aG9ncLKD8AKb3wOCcRgmZAQGtkPpk-Jw~~",
    "showTopPosition": false,
    "skills": [
        "自动化测试经验",
        "VLAN, OSPF,",
        "自动化测试",
        "TCP/IP, UDP,  BGP",
        "python自动化",
        "二三层转发",
        "Python",
        "BRAS、路由器相关测试"
    ],
    "welfareList": [
        "补充医疗保险",
        "五险一金"
    ]
}