{
    "anonymous": 0,
    "areaDistrict": "万柏林区",
    "atsDirectPost": false,
    "bossAvatar": "https://img.bosszhipin.com/beijin/mcs/useravatar/20180204/40d619975c492f2e028d3a0e955b21522dc12607d5ade6ae9ff59c294394c231_s.jpg",
    "bossCert": 3,
    "bossName": "冯千喜",
    "bossOnline": false,
    "bossTitle": "人力资源",
    "brandIndustry": "工程施工",
    "brandLogo": "https://img.bosszhipin.com/beijin/icon/894ce6fa7e58d64d57e7f22d2f3a9d18afa7fcceaa24b8ea28f56f1bb14732c0.png",
    "brandName": "融辰建筑工程",
    "brandScaleName": "500-999人",
    "brandStageName": "",
    "businessDistrict": "晋祠",
    "city": 101100100,
    "cityName": "太原",
    "contact": false,
    "daysPerWeekDesc": "",
    "encryptBossId": "5873cfd4c6cd74e11XR53dq5ElQ~",
    "encryptBrandId": "c285953d8d8d056c0nd_3d2_",
    "encryptJobId": "efbc1af4b49b80881ndz3ty8FFc~",
    "expectId": 975728182,
    "goldHunter": 0,
    "gps": null,
    "iconFlagList": [],
    "iconWord": "",
    "industry": 100702,
    "isShield": 0,
    "itemId": 149,
    "jobDegree": "大专",
    "jobExperience": "在校/应届",
    "jobLabels": [
        "在校/应届",
        "大专"
    ],
    "jobName": "IOS手机软件开发 双休",
    "jobType": 5,
    "jobValidStatus": 1,
    "leastMonthDesc": "",
    "lid": "a3DDPsnsXSr.search.149",
    "optimal": 0,
    "outland": 0,
    "proxyJob": 0,
    "proxyType": 0,
    "salaryDesc": "3-6K",
    "securityId": "-bnm9zM6VBmXW-t1nTid4J7rCx0u8T0f4pEbKTS4kv1-BFyH07pj4KfgiQyEr04VBWNyht96Oft8lwSzq7VRKDQ4DWTkVM1WNG-Di-xLwHJIrnTabk1tu1EsDT6ACZNdTsc8jwXZ",
    "showTopPosition": false,
    "skills": [
        "iOS"
    ],
    "welfareList": []
}