{
    "anonymous": 0,
    "areaDistrict": "芙蓉区",
    "atsDirectPost": false,
    "bossAvatar": "https://img.bosszhipin.com/boss/avatar/avatar_1.png",
    "bossCert": 3,
    "bossName": "杨女士",
    "bossOnline": false,
    "bossTitle": "人事",
    "brandIndustry": "医疗服务",
    "brandLogo": "https://img.bosszhipin.com/beijin/icon/894ce6fa7e58d64d57e7f22d2f3a9d18afa7fcceaa24b8ea28f56f1bb14732c0.png",
    "brandName": "药大检测",
    "brandScaleName": "20-99人",
    "brandStageName": "未融资",
    "businessDistrict": "湖南农业大学",
    "city": 101250100,
    "cityName": "长沙",
    "contact": false,
    "daysPerWeekDesc": "",
    "encryptBossId": "3a89f1882b9aee690nZ439-0FFFY",
    "encryptBrandId": "d35d7967e08feaf21Xd72tu-FFI~",
    "encryptJobId": "cb3189e2a2fe5bb91HZ609-5FFJV",
    "expectId": 0,
    "goldHunter": 0,
    "gps": null,
    "iconFlagList": [],
    "iconWord": "",
    "industry": 100402,
    "isShield": 0,
    "itemId": 294,
    "jobDegree": "大专",
    "jobExperience": "1-3年",
    "jobLabels": [
        "1-3年",
        "大专"
    ],
    "jobName": "质量体系工程师",
    "jobType": 0,
    "jobValidStatus": 1,
    "leastMonthDesc": "",
    "lid": "6CrEfZ5rbZs.search.294",
    "optimal": 0,
    "outland": 0,
    "proxyJob": 0,
    "proxyType": 0,
    "salaryDesc": "4-5K",
    "securityId": "OPyi6ipXvcxMU-s1uzhWm5OsIclsSsXLtCB0-QUWv4sUWOLittEZ68cOgdBYPVjowXOaIN1FuS7zrkYTUfQdou0HS8W80qDI-gPl8XkQo1yQr6eMXAdP",
    "showTopPosition": false,
    "skills": [
        "CMA、CNAS"
    ],
    "welfareList": []
}