{
    "anonymous": 0,
    "areaDistrict": "滨江区",
    "atsDirectPost": false,
    "bossAvatar": "https://img.bosszhipin.com/beijin/upload/avatar/20210423/c28488a9b4c64bf420c1fa3e972c1b92abaa41c67c2cb32fb2d2cdde7a7e59c5_s.jpg",
    "bossCert": 3,
    "bossName": "王女士",
    "bossOnline": false,
    "bossTitle": "HR",
    "brandIndustry": "电子商务",
    "brandLogo": "https://img.bosszhipin.com/beijin/upload/com/workfeel/20240219/7bf6f160950405e9d39be23efa63b42f08fdef39c6e1d271911180b2e28ade34ca343bb19c5fee11.png.webp",
    "brandName": "彤云晓聚",
    "brandScaleName": "20-99人",
    "brandStageName": "不需要融资",
    "businessDistrict": "长河",
    "city": 101210100,
    "cityName": "杭州",
    "contact": false,
    "daysPerWeekDesc": "",
    "encryptBossId": "c7c869475ae96c3d03Z92t69F1c~",
    "encryptBrandId": "bb8019e3072b95561HV60tW5FlQ~",
    "encryptJobId": "67a00bb7bebacc8c03R92N2_FlFR",
    "expectId": 1014042683,
    "goldHunter": 0,
    "gps": {
        "latitude": 30.185021,
        "longitude": 120.201846
    },
    "iconFlagList": [],
    "iconWord": "",
    "industry": 100001,
    "isShield": 0,
    "itemId": 279,
    "jobDegree": "大专",
    "jobExperience": "1年以内",
    "jobLabels": [
        "1年以内",
        "大专"
    ],
    "jobName": "微信社群运营助理",
    "jobType": 0,
    "jobValidStatus": 1,
    "leastMonthDesc": "",
    "lid": "9UaDBSN0Q3w.search.279",
    "optimal": 0,
    "outland": 0,
    "proxyJob": 0,
    "proxyType": 0,
    "salaryDesc": "4-6K",
    "securityId": "pbZs0IstfagIB-x14rq2kpdSXu7BVVmqlM4jIEdARYZZg_MWue6xji10rBwnZK3hKoKevvNKEmzvK9EXrrXI6i-s_0lidWu2KVuB8nH6jDJdDYl3XtDjFSm3Xlho8Gwes0sLdJv2tEp6lg~~",
    "showTopPosition": false,
    "skills": [
        "用户运营",
        "社区运营"
    ],
    "welfareList": [
        "年终奖",
        "底薪加提成",
        "全勤奖",
        "绩效奖金",
        "零食下午茶",
        "五险一金",
        "餐补",
        "员工旅游",
        "加班补助",
        "带薪年假",
        "工龄奖",
        "保底工资",
        "团建聚餐"
    ]
}