{
    "afterNameIcons": [],
    "anonymous": 0,
    "areaDistrict": "拱墅区",
    "atsDirectPost": false,
    "beforeNameIcons": [],
    "bossAvatar": "https://img.bosszhipin.com/beijin/upload/avatar/20240303/607f1f3d68754fd0058e46eee58df72687870be7ca5fe715404872b45046314ab92c6b4ab45e2f6a_s.png.webp",
    "bossCert": 3,
    "bossName": "邹女士",
    "bossOnline": false,
    "bossTitle": "人事专员",
    "brandIndustry": "电气机械/器材",
    "brandLogo": "https://img.bosszhipin.com/beijin/upload/com/workfeel/20240111/7bf6f160950405e960e35fdcf85b2625b1c76dbbe5d27cc5f34b7118f410e82fbaf8f4a3ba6a4742.png.webp",
    "brandName": "杭州昆泰磁悬浮",
    "brandScaleName": "100-499人",
    "brandStageName": "天使轮",
    "businessDistrict": "文一路",
    "city": 101210100,
    "cityName": "杭州",
    "contact": false,
    "daysPerWeekDesc": "",
    "encryptBossId": "a94e4250beb1f42903By3du-FVY~",
    "encryptBrandId": "d19174e560645e5e1XJ83t66FVY~",
    "encryptJobId": "2cdfb862b49668f503R-0t6-EFtU",
    "expectId": 1014042683,
    "goldHunter": 0,
    "gps": {
        "latitude": 30.299227,
        "longitude": 120.117564
    },
    "iconFlagList": [],
    "iconWord": "",
    "industry": 100908,
    "isShield": 0,
    "itemId": 280,
    "jobDegree": "大专",
    "jobExperience": "1-3年",
    "jobLabels": [
        "1-3年",
        "大专"
    ],
    "jobName": "硬件测试工程师",
    "jobType": 0,
    "jobValidStatus": 1,
    "leastMonthDesc": "",
    "lid": "4xfMxjDazFc.search.280",
    "optimal": 0,
    "outland": 0,
    "proxyJob": 0,
    "proxyType": 0,
    "salaryDesc": "6-10K·13薪",
    "securityId": "pWPiJpjkehKZY-G1t7sZ-gUC4KyUwM-UXgIp-ZWy5d0Bx3O3v0Bq0mCfe2EozcmhiuJz2brC7-QnWst6twUWst-IvoWZ4I7vJB-YZwYz2agjWK_KCJzWjlq-CyhNxPg602jL7LWmq9CTZw~~",
    "showTopPosition": false,
    "skills": [
        "智能硬件类",
        "通信设备类",
        "手机/电脑硬件类"
    ],
    "welfareList": [
        "生日福利",
        "带薪年假",
        "团建聚餐",
        "意外险",
        "节日福利",
        "绩效奖金",
        "定期体检",
        "年终奖",
        "五险一金"
    ]
}