{
    "anonymous": 0,
    "areaDistrict": "西湖区",
    "atsDirectPost": false,
    "bossAvatar": "https://img.bosszhipin.com/boss/avatar/avatar_6.png",
    "bossCert": 3,
    "bossName": "熊先生",
    "bossOnline": true,
    "bossTitle": "招聘经理",
    "brandIndustry": "计算机软件",
    "brandLogo": "https://img.bosszhipin.com/beijin/mcs/banner/b9fa12dd0bfae135a91b57eebeebca3dcfcd208495d565ef66e7dff9f98764da.jpg",
    "brandName": "中电金信",
    "brandScaleName": "10000人以上",
    "brandStageName": "B轮",
    "businessDistrict": "黄龙",
    "city": 101210100,
    "cityName": "杭州",
    "contact": false,
    "daysPerWeekDesc": "",
    "encryptBossId": "a3c3d0b4dfe658e31H1z3tu0F1s~",
    "encryptBrandId": "9e1bceeac44be7361nd80tq6E1U~",
    "encryptJobId": "9e9056614336d0061HN42ty4E1VT",
    "expectId": 0,
    "goldHunter": 0,
    "gps": null,
    "iconFlagList": [],
    "iconWord": "",
    "industry": 100021,
    "isShield": 0,
    "itemId": 37,
    "jobDegree": "大专",
    "jobExperience": "1-3年",
    "jobLabels": [
        "1-3年",
        "大专"
    ],
    "jobName": "数据结算",
    "jobType": 0,
    "jobValidStatus": 1,
    "leastMonthDesc": "",
    "lid": "7v7AxFclTOO.search.37",
    "optimal": 0,
    "outland": 0,
    "proxyJob": 0,
    "proxyType": 0,
    "salaryDesc": "5-7K",
    "securityId": "OpzzEJtH5A9sN-G1r_XW7aeSdyc6l9FTLEt_1Cp1mNINqcpoUkn8ENkLYopfTPVxhLx7k2YKs_dAZMeC6-hh01Xp1erSyrfWUJThld8AgT8c7e1kRLjJO0ldz81dRhZWVu_btZv8Z6XGj1I4v0pAQMw~",
    "showTopPosition": false,
    "skills": [
        "数据分析"
    ],
    "welfareList": [
        "补充医疗保险",
        "五险一金",
        "节日福利",
        "定期体检"
    ]
}